meteo_render/__init__.py
meteo_render/__main__.py
meteo_render/config.py
meteo_render/render.py
meteo_render/templates/family/img/0.png
meteo_render/templates/family/img/1.png
meteo_render/templates/family/img/2.png
meteo_render/templates/family/img/3.png
meteo_render/templates/family/img/45.png
meteo_render/templates/family/img/51.png
meteo_render/templates/family/img/53.png
meteo_render/templates/family/img/55.png
meteo_render/templates/family/img/61.png
meteo_render/templates/family/img/63.png
meteo_render/templates/family/img/65.png
meteo_render/templates/family/img/71.png
meteo_render/templates/family/img/73.png
meteo_render/templates/family/img/75.png
meteo_render/templates/family/img/80.png
meteo_render/templates/family/img/85.png
meteo_render/templates/family/img/86.png
meteo_render/templates/family/img/95.png
meteo_render/templates/family/img/99.png
meteo_render/templates/family/img/XXX.png
meteo_render/templates/family/page.html.j2
meteo_render/templates/family/style.css
meteo_render-0.5.2.dist-info/METADATA
meteo_render-0.5.2.dist-info/WHEEL
meteo_render-0.5.2.dist-info/RECORD
