Metadata-Version: 2.1
Name: meteo-render
Version: 0.5.2
Summary: Retrieve open-meteo.com data and render it into HTML pages
License: MIT
Author: Jack Grahl
Author-email: jack.grahl@gmail.com
Requires-Python: >=3.7,<4.0
Classifier: License :: OSI Approved :: MIT License
Classifier: Programming Language :: Python :: 3
Classifier: Programming Language :: Python :: 3.7
Classifier: Programming Language :: Python :: 3.8
Classifier: Programming Language :: Python :: 3.9
Classifier: Programming Language :: Python :: 3.10
Classifier: Programming Language :: Python :: 3.11
Requires-Dist: Jinja2 (>=3.1.2,<4.0.0)
Requires-Dist: pytz (>=2023.3,<2024.0)
Requires-Dist: requests (>=2.28.2,<3.0.0)
